jinja2_humanize_extension/__init__.py
jinja2_humanize_extension-0.3.0.dist-info/LICENSE
jinja2_humanize_extension-0.3.0.dist-info/METADATA
jinja2_humanize_extension-0.3.0.dist-info/WHEEL
jinja2_humanize_extension-0.3.0.dist-info/top_level.txt
jinja2_humanize_extension-0.3.0.dist-info/RECORD
