Metadata-Version: 2.1
Name: jinja2-humanize-extension
Version: 0.3.0
Summary: a jinja2 extension to use humanize library inside jinja2 templates
Home-page: https://github.com/metwork-framework/jinja2_humanize_extension
Author: Fabien MARTY
Author-email: fabien.marty@gmail.com
License: BSD
Keywords: jinja2 extension
Classifier: Development Status :: 5 - Production/Stable
Classifier: Intended Audience :: Developers
Classifier: License :: OSI Approved :: BSD License
Classifier: Programming Language :: Python :: 3
Requires-Python: >=3.0
License-File: LICENSE
Requires-Dist: jinja2
Requires-Dist: humanize (>=3.14.0)
